{"index":{"links":{"/notes/Continuous-Function":[{"source":"/notes/Continuous-Function","target":"/notes/Topological-Space","text":"topological spaces"}],"/notes/Exact-Inference":[{"source":"/notes/Exact-Inference","target":"/notes/Gaussian-Belief-Propagation-GBP","text":"notes/Gaussian Belief Propagation (GBP)"}],"/notes/Exponential-Families":[{"source":"/notes/Exponential-Families","target":"/notes/Graphical-Models","text":"notes/Graphical Models"},{"source":"/notes/Exponential-Families","target":"/notes/Ising-Model","text":"notes/Ising Model"},{"source":"/notes/Exponential-Families","target":"/notes/Gaussian-MRF","text":"notes/Gaussian MRF"},{"source":"/notes/Exponential-Families","target":"/notes/Gaussian-Mixture-Model","text":"notes/Gaussian Mixture Model"}],"/notes/Gaussian-Belief-Propagation-GBP":[{"source":"/notes/Gaussian-Belief-Propagation-GBP","target":"/notes/Graphical-Models","text":"PGMs"},{"source":"/notes/Gaussian-Belief-Propagation-GBP","target":"/notes/Exact-Inference","text":"notes/Exact Inference"}],"/notes/Gaussian-MRF":[{"source":"/notes/Gaussian-MRF","target":"/notes/Graphical-Models","text":"markov random field"}],"/notes/Gaussian-Mixture-Model":[{"source":"/notes/Gaussian-Mixture-Model","target":"/notes/Exponential-Families","text":"exponential family"},{"source":"/notes/Gaussian-Mixture-Model","target":"/notes/Graphical-Models","text":"notes/Graphical Models"},{"source":"/notes/Gaussian-Mixture-Model","target":"/notes/Exponential-Families","text":"exponential family"},{"source":"/notes/Gaussian-Mixture-Model","target":"/notes/Graphical-Models","text":"notes/Graphical Models"}],"/notes/Homeomorphism":[{"source":"/notes/Homeomorphism","target":"/notes/Topological-Space","text":"topological spaces"},{"source":"/notes/Homeomorphism","target":"/notes/Continuous-Function","text":"continuous"}],"/notes/Ising-Model":[{"source":"/notes/Ising-Model","target":"/notes/Graphical-Models","text":"graphical model"},{"source":"/notes/Ising-Model","target":"/notes/Exponential-Families","text":"exponential family"}],"/notes/Variational-Inference":[{"source":"/notes/Variational-Inference","target":"/notes/Exact-Inference","text":"notes/Exact Inference"}]},"backlinks":{"/notes/Continuous-Function":[{"source":"/notes/Homeomorphism","target":"/notes/Continuous-Function","text":"continuous"}],"/notes/Exact-Inference":[{"source":"/notes/Gaussian-Belief-Propagation-GBP","target":"/notes/Exact-Inference","text":"notes/Exact Inference"},{"source":"/notes/Variational-Inference","target":"/notes/Exact-Inference","text":"notes/Exact Inference"}],"/notes/Exponential-Families":[{"source":"/notes/Gaussian-Mixture-Model","target":"/notes/Exponential-Families","text":"exponential family"},{"source":"/notes/Gaussian-Mixture-Model","target":"/notes/Exponential-Families","text":"exponential family"},{"source":"/notes/Ising-Model","target":"/notes/Exponential-Families","text":"exponential family"}],"/notes/Gaussian-Belief-Propagation-GBP":[{"source":"/notes/Exact-Inference","target":"/notes/Gaussian-Belief-Propagation-GBP","text":"notes/Gaussian Belief Propagation (GBP)"}],"/notes/Gaussian-MRF":[{"source":"/notes/Exponential-Families","target":"/notes/Gaussian-MRF","text":"notes/Gaussian MRF"}],"/notes/Gaussian-Mixture-Model":[{"source":"/notes/Exponential-Families","target":"/notes/Gaussian-Mixture-Model","text":"notes/Gaussian Mixture Model"}],"/notes/Graphical-Models":[{"source":"/notes/Exponential-Families","target":"/notes/Graphical-Models","text":"notes/Graphical Models"},{"source":"/notes/Gaussian-Belief-Propagation-GBP","target":"/notes/Graphical-Models","text":"PGMs"},{"source":"/notes/Gaussian-MRF","target":"/notes/Graphical-Models","text":"markov random field"},{"source":"/notes/Gaussian-Mixture-Model","target":"/notes/Graphical-Models","text":"notes/Graphical Models"},{"source":"/notes/Gaussian-Mixture-Model","target":"/notes/Graphical-Models","text":"notes/Graphical Models"},{"source":"/notes/Ising-Model","target":"/notes/Graphical-Models","text":"graphical model"}],"/notes/Ising-Model":[{"source":"/notes/Exponential-Families","target":"/notes/Ising-Model","text":"notes/Ising Model"}],"/notes/Topological-Space":[{"source":"/notes/Continuous-Function","target":"/notes/Topological-Space","text":"topological spaces"},{"source":"/notes/Homeomorphism","target":"/notes/Topological-Space","text":"topological spaces"}]}},"links":[{"source":"/notes/Continuous-Function","target":"/notes/Topological-Space","text":"topological spaces"},{"source":"/notes/Exact-Inference","target":"/notes/Gaussian-Belief-Propagation-GBP","text":"notes/Gaussian Belief Propagation (GBP)"},{"source":"/notes/Exponential-Families","target":"/notes/Graphical-Models","text":"notes/Graphical Models"},{"source":"/notes/Exponential-Families","target":"/notes/Ising-Model","text":"notes/Ising Model"},{"source":"/notes/Exponential-Families","target":"/notes/Gaussian-MRF","text":"notes/Gaussian MRF"},{"source":"/notes/Exponential-Families","target":"/notes/Gaussian-Mixture-Model","text":"notes/Gaussian Mixture Model"},{"source":"/notes/Gaussian-Belief-Propagation-GBP","target":"/notes/Graphical-Models","text":"PGMs"},{"source":"/notes/Gaussian-Belief-Propagation-GBP","target":"/notes/Exact-Inference","text":"notes/Exact Inference"},{"source":"/notes/Gaussian-MRF","target":"/notes/Graphical-Models","text":"markov random field"},{"source":"/notes/Gaussian-Mixture-Model","target":"/notes/Exponential-Families","text":"exponential family"},{"source":"/notes/Gaussian-Mixture-Model","target":"/notes/Graphical-Models","text":"notes/Graphical Models"},{"source":"/notes/Gaussian-Mixture-Model","target":"/notes/Exponential-Families","text":"exponential family"},{"source":"/notes/Gaussian-Mixture-Model","target":"/notes/Graphical-Models","text":"notes/Graphical Models"},{"source":"/notes/Homeomorphism","target":"/notes/Topological-Space","text":"topological spaces"},{"source":"/notes/Homeomorphism","target":"/notes/Continuous-Function","text":"continuous"},{"source":"/notes/Ising-Model","target":"/notes/Graphical-Models","text":"graphical model"},{"source":"/notes/Ising-Model","target":"/notes/Exponential-Families","text":"exponential family"},{"source":"/notes/Variational-Inference","target":"/notes/Exact-Inference","text":"notes/Exact Inference"}]}